aurras/__init__.py
aurras/aurras_cli/__main__.py
aurras/aurras_tui/__main__.py
aurras/core/__init__.py
aurras/core/downloader.py
aurras/core/backup/__init__.py
aurras/core/backup/manager.py
aurras/core/backup/restore.py
aurras/core/backup/storage.py
aurras/core/backup/utils.py
aurras/core/cache/__init__.py
aurras/core/cache/initialize.py
aurras/core/cache/loader.py
aurras/core/cache/search_db.py
aurras/core/cache/updater.py
aurras/core/player/__init__.py
aurras/core/player/cache.py
aurras/core/player/history.py
aurras/core/player/memory.py
aurras/core/player/offline.py
aurras/core/player/online.py
aurras/core/player/python_mpv.py
aurras/core/player/mpv/__init__.py
aurras/core/player/mpv/core.py
aurras/core/player/mpv/events.py
aurras/core/player/mpv/history_integration.py
aurras/core/player/mpv/keyboard.py
aurras/core/player/mpv/lyrics_integration.py
aurras/core/player/mpv/search_integration.py
aurras/core/player/mpv/state.py
aurras/core/player/mpv/ui.py
aurras/core/playlist/__init__.py
aurras/core/playlist/download.py
aurras/core/playlist/manager.py
aurras/core/playlist/sync.py
aurras/core/playlist/cache/__init__.py
aurras/core/playlist/cache/initialize.py
aurras/core/playlist/cache/loader.py
aurras/core/playlist/cache/search_db.py
aurras/core/playlist/cache/updater.py
aurras/core/settings/__init__.py
aurras/core/settings/io.py
aurras/core/settings/updater.py
aurras/core/settings/models/__init__.py
aurras/core/settings/models/appearance.py
aurras/core/settings/models/backup.py
aurras/core/settings/models/base.py
aurras/core/settings/models/command.py
aurras/core/settings/models/keyboard.py
aurras/core/settings/models/shorthand.py
aurras/core/settings/models/utils.py
aurras/core/settings/models/validators.py
aurras/services/__init__.py
aurras/services/lyrics/__init__.py
aurras/services/lyrics/cache.py
aurras/services/lyrics/fetcher.py
aurras/services/lyrics/formatter.py
aurras/services/lyrics/manager.py
aurras/services/lyrics/parser.py
aurras-2.0.2.dist-info/licenses/LICENSE.txt
aurras-2.0.2.dist-info/METADATA
aurras-2.0.2.dist-info/WHEEL
aurras-2.0.2.dist-info/entry_points.txt
aurras-2.0.2.dist-info/top_level.txt
aurras-2.0.2.dist-info/RECORD
