Metadata-Version: 2.4
Name: aurras
Version: 2.0.2
Summary: A high-end command line music player
Author-email: vedant-asati03 <vedant.asati03@gmail.com>
License-Expression: MIT
Project-URL: repository, https://github.com/vedant-asati03/Aurras
Keywords: music,player,audio,cli,terminal,youtube,spotify
Classifier: Development Status :: 4 - Beta
Classifier: Intended Audience :: End Users/Desktop
Classifier: Programming Language :: Python :: 3
Classifier: Programming Language :: Python :: 3.12
Classifier: Programming Language :: Python :: 3.13
Classifier: Topic :: Multimedia :: Sound/Audio :: Players
Requires-Python: <4.0.0,>=3.12
License-File: LICENSE.txt
Requires-Dist: aiosqlite>=0.18.0
Requires-Dist: argparse>=1.4.0
Requires-Dist: pillow>=9.0.0
Requires-Dist: prompt-toolkit>=3.0.0
Requires-Dist: pydantic>=2.0.0
Requires-Dist: pyyaml>=6.0
Requires-Dist: questionary>=1.10.0
Requires-Dist: requests>=2.28.0
Requires-Dist: rich>=12.0.0
Requires-Dist: spotdl>=4.0.0
Requires-Dist: spotipy>=2.25.1
Requires-Dist: sqlitedict>=2.1.0
Requires-Dist: syncedlyrics>=0.6.0
Requires-Dist: textual>=0.31.0
Requires-Dist: ytmusicapi>=0.24.0
Dynamic: license-file
